{
    "status": {
        "code": "1",
        "text": "获取知识列表成功！"
    },
    "custom": {
        "num": 6088,
        "infoList": [
            {
                "publishTime": "2023-04-03 09:12:03",
                "kinfoContent": "急难型救助对象如何认定？答：发生火灾、交通事故、溺水等意外事件造成重大人员伤亡；家庭成员突发重大疾病，需紧急入院抢救；遭遇其他特殊困难等。急难型救助对象，只需确定是否发生急难事项影响到基本生活且依靠自身无力克服当前困难，两个条件同时满足即可实施救助。",
                "kinfoName": "急难型救助对象如何认定？",
                "ispublic": "true",
                "kinfoGuid": "dd117d9b-a8a4-4d85-ad17-c6e529755cb4",
                "categoryName": "社会救助",
                "visitTimes": 17
            },
            {
                "publishTime": "2023-04-03 09:06:26",
                "kinfoContent": "截止2022年末，荆门市共有企业68994家。",
                "kinfoName": "请问2022年荆门市有多少家企业？",
                "ispublic": "true",
                "kinfoGuid": "90e63368-8270-433d-8561-bda8182bfdb4",
                "categoryName": "机构职能",
                "visitTimes": 2
            },
            {
                "publishTime": "2023-03-31 16:57:35",
                "kinfoContent": "（1)侵占人防工程；（2)改变人防工程的主体结构；（3)偷窃、损毁、拆除人防工程的设备、设施；（4)在人防工程内或者安全保护范围内，生产、经营或者储存爆炸性、易燃性、放射性、毒害性、腐蚀性等危险物资；（5)向人防工程内或者安全保护范围内排入废水、废气或者倾倒废弃物；（6)占用、堵塞人防工程的进出道路和通风、出入等孔口；（7)在人防工程进出口部和人防工程出入通道内建造建筑物和构筑物：（8)在人防工程安全保护范围内进行采石、取土、钻探、爆破、打桩等作业：（9)法律、法规和规章禁止的其他危害人防工程安全和使用效能的行为。",
                "kinfoName": "哪些属于危害人防工程的行为？",
                "ispublic": "true",
                "kinfoGuid": "2388bfdb-910c-4911-bbc8-65c50ec1f6bc",
                "categoryName": "人防工程",
                "visitTimes": 38
            },
            {
                "publishTime": "2023-03-31 16:53:33",
                "kinfoContent": "（1)掘开式单建人防工程围护外墙向外延伸5米以内及结构顶板上方垂直距离1米以内；（2)坑道式、地道式单建人防工程围护外墙向外延伸5米以内及结构顶板上方垂直距离5米以内；（3)防空地下室围护外墙向外延伸3米以内。",
                "kinfoName": "人防工程安全的保护范围",
                "ispublic": "true",
                "kinfoGuid": "3ef5d09f-aede-415c-ab78-d777e72905bc",
                "categoryName": "人防工程",
                "visitTimes": 23
            },
            {
                "publishTime": "2023-03-31 16:50:07",
                "kinfoContent": "（1)人防通道：卫生符合要求、通道内无积水、门扇开启正常、设备设施无损坏；（2)排水系统：排水沟（坑）内无杂物、排水泵工作正常。（3)通风系统：风机工作正常、进排风量正常。（4)消防系统：工作正常，符合消防规范要求。不得在工程内部堆放易燃易爆物品。（5)人防设备：无锈蚀、无丢失、无损坏。（6)工程结构：不得打孔、破坏钢筋混凝土墙体、顶板等结构。（7)应急情况：防水物资器材准备充分、防汛物资到位。（8)其他：人防工程符合平时使用要求，结构及内部系统安全可靠，没有严重安全隐患。",
                "kinfoName": "人防工程维护管理要点",
                "ispublic": "true",
                "kinfoGuid": "576455f2-e7e4-4194-861c-d01664ba381d",
                "categoryName": "人防工程",
                "visitTimes": 19
            },
            {
                "publishTime": "2023-03-31 09:37:11",
                "kinfoContent": "对小型微利企业年应纳税所得额不超过100万元的部分，自2021年1月1日至2022年12月31日，减按12.5%计入应纳税所得额，按20%的税率缴纳企业所得税。对小型微利企业年应纳税所得额超过100万元但不超过300万元的部分，自2022年1月1日至2024年12月31日，减按25%计入应纳税所得额，按20%的税率缴纳企业所得税。小型微利企业无论按查账征收方式或核定征收方式缴纳企业所得税，均可享受上述优惠政策。",
                "kinfoName": "小型微利企业的企业所得税应纳税所得额的优惠有哪些？",
                "ispublic": "true",
                "kinfoGuid": "c388d619-f81c-40cb-8881-65fb435e1ae9",
                "categoryName": "惠企政策",
                "visitTimes": 9
            },
            {
                "publishTime": "2023-03-31 09:35:49",
                "kinfoContent": "企业应纳税所得额的计算，以权责发生制为原则，属于当期的收入和费用，不论款项是否收付，均作为当期的收入和费用;不属于当期的收入和费用，即使款项已经在当期收付，均不作为当期的收入和费用。",
                "kinfoName": "企业所得税按照什么原则确定收入？",
                "ispublic": "true",
                "kinfoGuid": "a93247e0-c672-4744-a1fb-d7f0f662cad9",
                "categoryName": "税收政策",
                "visitTimes": 14
            },
            {
                "publishTime": "2023-03-31 09:35:00",
                "kinfoContent": "企业以货币形式和非货币形式从各种来源取得的收入，为收入总额。包括：(一)销售货物收入；(二)提供劳务收入；(三)转让财产收入；(四)股息、红利等权益性投资收益；(五)利息收入；(六)租金收入；(七)特许权使用费收入；(八)接受捐赠收入；(九)其他收入。",
                "kinfoName": "企业所得税的收入有哪些？",
                "ispublic": "true",
                "kinfoGuid": "bda37fef-7239-4fa8-898b-6a75ad2f427f",
                "categoryName": "税收政策",
                "visitTimes": 10
            },
            {
                "publishTime": "2023-03-29 15:35:04",
                "kinfoContent": "（1）居民身份证、临时居民身份证;（2）中国人民解放军军人身份证件、中国人民武装警察身份证件;（3）港澳台居民居住证、港澳居民来往内地通行证、台湾居民来往大陆通行证;（4）外国公民护照;（5）国家规定的其他有效身份证件。",
                "kinfoName": "哪些证件属于寄件人出示的有效身份证件",
                "ispublic": "true",
                "kinfoGuid": "95028352-7ed6-4d43-a9f6-290c33f2a2f2",
                "categoryName": "邮政快递管理",
                "visitTimes": 35
            },
            {
                "publishTime": "2023-03-29 15:31:35",
                "kinfoContent": "寄递企业应严格执行实名收寄制度。在收寄邮件快件时,依法要求寄件人出示有效身份证件,对寄件人身份进行查验,并登记身份信息。有效身份证件要求提供证件原件,不应包含复印件、扫描件、照片等。",
                "kinfoName": "实名收寄制度中实名查验具体要求",
                "ispublic": "true",
                "kinfoGuid": "112c24b9-95b9-4e27-a354-fe373835e607",
                "categoryName": "邮政快递管理",
                "visitTimes": 12
            },
            {
                "publishTime": "2023-03-29 15:29:01",
                "kinfoContent": "邮件快件可采用营业场所收寄、协议用户收寄、上门收寄和智能收投服务终端收寄四种方式。（1）营业场所收寄是通过营业网点完成收寄的服务方式;（2）协议用户收寄是对签订寄递协议的交寄量大或交寄频次高的寄件人提供批量交寄的服务方式;（3）上门收寄是收派员到寄件人现场完成收寄的服务方式;（4）智能收投服务终端收寄是通过智能快件箱、智能远程收寄终端等设备完成收寄的服务方式。",
                "kinfoName": "邮件快件收寄的几种方式",
                "ispublic": "true",
                "kinfoGuid": "b1e40a36-6f32-4a36-aa4b-7450872b91b4",
                "categoryName": "邮政快递管理",
                "visitTimes": 22
            },
            {
                "publishTime": "2023-03-29 08:51:27",
                "kinfoContent": "甲型流感症状比普通感冒更严重，危害性也更大，可能诱发肺炎、加重基础病。作为一种自限性疾病，治疗上也有多种抗病毒药物，早期服用可以缩短病程、减轻症状、降低重症风险，建议在症状较重、重症风险较高的情况下使用。当然，也不是每个甲流患者都需要使用抗病毒药物，还是得视症状、重症风险而定。",
                "kinfoName": "感染甲流要服用抗病毒药物吗？",
                "ispublic": "true",
                "kinfoGuid": "82aaaf41-690b-44d2-b978-dbd776dedcac",
                "categoryName": "卫生医疗知识",
                "visitTimes": 45
            },
            {
                "publishTime": "2023-03-29 08:49:37",
                "kinfoContent": "首先，普通感冒一般发热症状不会太厉害，而甲流可能高烧39°以上。其次，普通感冒一般经历2天左右的流涕、咳嗽后，症状会很快好转；而甲流发病症状较为严重，且会持续3~5天，严重的话可能5~7天。如果你出现了疑似甲流的上呼吸道症状，建议进行流感抗原筛查，确诊后再进行药物治疗。感染甲流后出现症状的第二天或者发烧后就能进行检测，可以进行抗原自测，也可以前往医院进行核酸检测，准确性会更高一些。以下情况，建议尽早就医1.5岁以下儿童感染；2.存在基础疾病的儿童感染；3.服药后症状没有缓解，精神差，呕吐腹泻；4.服药过程中出现症状反弹。",
                "kinfoName": "如何判断是否感染甲流？",
                "ispublic": "true",
                "kinfoGuid": "5405367d-20d6-48f0-9359-abb61d892851",
                "categoryName": "卫生医疗知识",
                "visitTimes": 37
            },
            {
                "publishTime": "2023-03-28 11:07:14",
                "kinfoContent": "法定四种不适用无理由退货的情形：一是消费者定做的。二是鲜活易腐的商品。三是在线下载或者消费者拆封的音像制品、计算机软件等数字化商品。四是已经交付的报纸、期刊。除上述四项法定排除情形外，还有一种对经营者和消费者约定排除适用的情形，即根据商品性质并经消费者在购买时确认不宜退货的，不适用无理由退货。",
                "kinfoName": "不适用无理由退货的情形有哪些？",
                "ispublic": "true",
                "kinfoGuid": "c3e9d108-d7a3-448c-b7d0-0d99feb3031f",
                "categoryName": "商品销售市场监管",
                "visitTimes": 24
            },
            {
                "publishTime": "2023-03-28 11:05:42",
                "kinfoContent": "财产损害包括金钱、时间、可得利益等损害。例如消费者购买假冒伪劣或者缺斤短两商品花出的冤枉钱；消费者因产品质量不合格导致生命健康损害后支出的护理费、交通费等治疗和康复费用，以及因误工减少的收入和残疾生活辅助具费用；消费者因退换不合格商品支出的交通费及误工损失费等。",
                "kinfoName": "消费者损害赔偿请求权的财产损害包括哪些？",
                "ispublic": "true",
                "kinfoGuid": "f41d00eb-f761-482e-b4ef-e32a4b024792",
                "categoryName": "商品销售市场监管",
                "visitTimes": 17
            },
            {
                "publishTime": "2023-03-28 11:04:46",
                "kinfoContent": "人身损害既包括对生命健康权、姓名权、肖像权、名誉权、隐私权的损害，也包括对人身自由、人格尊严等人格权的损害。例如因购买不合格商品或者服务导致死亡、伤残，在消费过程中遭到侮辱、谩骂,消费者的身体被搜查，消费者的个人秘密、个人信息被非法公开或者提供给他人，消费者的民族习惯没有得到尊重等。",
                "kinfoName": "消费者损害赔偿请求权的人身损害包括哪些？",
                "ispublic": "true",
                "kinfoGuid": "0a6d4335-c8dc-4b13-a4b3-43532d2eae47",
                "categoryName": "商品销售市场监管",
                "visitTimes": 12
            },
            {
                "publishTime": "2023-03-28 10:26:37",
                "kinfoContent": "沙洋县烟草制品零售点合理布局规划为维护国家烟草专卖制度，深化“放管服”改革，规范烟草专卖零售许可证管理，进一步优化烟草市场秩序，促进烟草市场健康有序发展，有效维护国家利益、消费者利益，切实保障烟草制品经营者、未成年人等相关群体的合法权益，根据《中华人民共和国行政许可法》《中华人民共和国烟草专卖法》《中华人民共和国未成年人保护法》《中华人民共和国烟草专卖法实施条例》《烟草专卖许可证管理办法》《烟草专卖许可证管理办法实施细则》等法律法规规章及规范性文件规定，遵循“依法行政、科学规划、服务社会、均衡发展”原则，结合实际，制定本规划。",
                "kinfoName": "沙洋县烟草制品零售点合理布局规划",
                "ispublic": "true",
                "kinfoGuid": "04cb2f54-148d-46b4-b37b-87b4855064c2",
                "categoryName": "证照办理",
                "visitTimes": 23
            },
            {
                "publishTime": "2023-03-24 18:34:58",
                "kinfoContent": "原在荆门市缴纳社保(医保、养老)，现返回钟祥市是否需办理社保转移后再缴费。一、原在荆门市缴纳社保，现返回钟祥市不需要办理社保转移后再缴费。二、原在荆门市缴纳医保，返回钟祥市首先要暂停荆门的医保。1、灵活就业人员，自己带身份证到政务服务大厅办理（代办的话由代办人员带身份证复印件）；2、单位职工，由单位直接在系统做增员。",
                "kinfoName": "原在荆门市缴纳社保(医保、养老)，现返回钟祥市是否需办理社保转移后再缴费。",
                "ispublic": "true",
                "kinfoGuid": "1a8e2ffb-4937-4cdc-8be2-86dc2235f0bd",
                "categoryName": "职工医疗保险",
                "visitTimes": 72
            },
            {
                "publishTime": "2023-03-23 18:05:49",
                "kinfoContent": "《市人民政府办公室关于印发鼓励支持各类科创主体入驻荆楚科创城政策措施等文件的通知》（荆政办发〔2021〕31号）中鼓励支持各类科创主体入驻荆楚科创城政策措施之人才引进政策：1.对在科创城新建的院士工作站、专家工作站、学会服务站，分别给予一次性建站补助20万元、10万元、10万元；对年度考核为优秀的，给予10万元奖励。（责任单位：市委人才办、市科协）对引进的高层次人才，年薪30万元以上的，在本地缴纳个人所得税地方留成部分，5年内每年按90%予以补贴。（责任单位：市委人才办、市税务局）对入选国家级、省级的重点人才项目，比照国家、省经费支持标准，给予50%的配套奖励。（责任单位：市委人才办）2.对全职引进的全日制博士、硕士研究生及普通高等教育本科生，每年分别给予3万元、2万元、1万元生活补助，连续补助3年；对科创城用人主体柔性引进的博士，一次性给予2万元生活交通补贴。对到科创城实习实训的大学生，按每人每月1000元标准发放生活补贴，最多发放3个月。（责任单位：市委人才办、市人社局）3.对科创城引进的各类科创人才，鼓励支持其在科创城核心区内租房、购房，并按照《荆楚科创城人才公寓租售管理方案》享受租房、购房补贴。（责任单位：市委人才办、市城控集团）对科创城引进的符合条件的全日制博士、硕士研究生、普通高等教育本科生，在科创城核心区以外的荆门中心城区购房的，经认定，分别一次性给予25万元、15万元、8万元的购房补助；对引进的领军人才，购房补助标准实行“一人一议”。（责任单位：市委人才办、市住建局）4.对到科创城创新创业的海内外领军人才、高端人才，经评审认定，在子女入学等方面开辟“绿色通道”，配偶需要随调的按照相关规定优先予以安排。（责任单位：市委人才办）",
                "kinfoName": "鼓励支持各类科创主体入驻荆楚科创城政策措施之人才引进政策",
                "ispublic": "true",
                "kinfoGuid": "2b5a4e9b-51d7-4b71-887f-e2cd70f64eff",
                "categoryName": "惠民惠企政策",
                "visitTimes": 124
            },
            {
                "publishTime": "2023-03-23 17:48:06",
                "kinfoContent": "《市人民政府办公室关于印发鼓励支持各类科创主体入驻荆楚科创城政策措施等文件的通知》（荆政办发〔2021〕31号）中鼓励支持各类科创主体入驻荆楚科创城政策措施之成果转化政策：1.对购买荆楚科创城科技成果并在市内转化、产业化的企业，由受益企业所在地按其技术合同实际支付额的10%给予最高不超过100万元的奖励。（责任单位：市科技局，各县市区）对入驻机构承担市内企业研发项目的，按照技术合同交易额到位资金的10%给予最高不超过200万元的奖励。（责任单位：市科技局）鼓励支持入驻科研机构就地转化孵化科技成果，在市域范围内转化的，按其成果转化所得税地方留成部分的100%给予一次性奖励；在市域范围外转化的，按其成果转化所得税地方留成部分的50%给予一次性奖励。（责任单位：市科技局、市财政局）2.对独立或牵头承担国家、省重大科技专项、重点研发计划项目的，按国家、省年度到位资金额的50%给予配套奖励。（责任单位：市科技局、市财政局）3.支持科技成果转化中试基地、科技企业孵化器和技术转移示范机构建设。对投资建设中试基地（平台）的，经评审认定，按其实际投资额的30%给予最高不超过500万元的补助。（责任单位：市科技局、市财政局）4.对纳入湖北省高新技术成果转化项目库、由市内企业首次实现转化的项目，按省定奖补标准给予1:1配套支持。（责任单位：市科技局、市财政局）对省级以上成果转化和技术转移机构，按省定绩效评价结果奖励标准给予1:1配套奖励。（责任单位：市科技局、市财政局）对获得国家级、省级科技成果奖励及湖北省企业研究开发费用后补助的，给予1:1配套奖补。（责任单位：市科技局、市财政局）",
                "kinfoName": "鼓励支持各类科创主体入驻荆楚科创城政策措施之成果转化政策",
                "ispublic": "true",
                "kinfoGuid": "53a167a4-57d3-4e2b-a700-009fb91a7757",
                "categoryName": "惠民惠企政策",
                "visitTimes": 38
            }
        ]
    }
}