{
    "status": {
        "code": "1",
        "text": "获取知识列表成功！"
    },
    "custom": {
        "num": 6088,
        "infoList": [
            {
                "publishTime": "2022-07-31 18:09:01",
                "kinfoContent": "省委、省政府高度重视乡村产业发展，提出农业产业强省的建设目标，明确重点发展十大产业：优质稻米、生猪、特色淡水产品（小龙虾）、蔬菜（食用菌、莲）、家禽及蛋制品、茶叶、现代种业、菜籽油、柑橘、道地药材。省财政拿出“真金白银”进行支持。从去年开始，连续五年，每年安排10亿元，支持以龙头企业为重点的经营主体发展（其中：每年安排5亿元，支持龙头企业开展科技攻关、农产品加工、关键设备购置、技术改造、冷链物流、人才培育、社会化服务、信息化建设等；每年统筹5亿元，对以龙头企业为重点的经营主体贷款进行贴息）。",
                "kinfoName": "湖北省明确的重点发展十大乡村产业",
                "kinfoGuid": "55cef37d-1abb-4572-b3bd-b90cfdae1bd1",
                "categoryName": "惠农补贴",
                "visitTimes": 7
            },
            {
                "publishTime": "2022-07-31 18:09:01",
                "kinfoContent": "当前位置：　荆门市公安局　　行政许可事项　　正文民用枪支配购许可证件核发　　1、事项名称：民用枪支配购许可证件核发　　2、设定依据：《中华人民共和国枪支管理法》　　3、申请条件：　　（一）经省级以上人民政府林业行政主管部门批准的狩猎场，可以配置猎枪；　　（二）野生动物保护、饲养、科研单位因业务需要，可以配置猎枪、麻醉注射枪；　　（三）猎民在猎区、牧民在牧区，可以申请配置猎枪。猎区和牧区的区域由省级人民政府划定。　　4、办理材料：　　（一）狩猎场配置猎枪，凭省级以上人民政府林业行政主管部门的批准文件，报省级人民政府公安机关审批，由设区的市级人民政府公安机关核发民用枪支配购证件；　　（二）野生动物保护、饲养、科研单位申请配置猎枪、麻醉注射枪的，应当凭其单位所在地的县级人民政府野生动物行政主管部门核发的狩猎证或者特许猎捕证和单位营业执照，向所在地的县级人民政府公安机关提出；　　（三）猎民申请配置猎枪的，应当凭其所在地的县级人民政府野生动物行政主管部门核发的狩猎证和个人身份证件，向所在地的县级人民政府公安机关提出。　　受理申请的公安机关审查批准后，应当报请设区的市级人民政府公安机关核发民用枪支配购证件。　　5、办理地点：市公安局治安支队治安科　　6、办理时间：即时办理，不收取费用　　7、联系电话：8882121　　8、办理流程：　　（一）申请：需要配置民用枪支的单位和个人向设区的市级人民政府公安机关申请核发民用枪支配购证件。　　（二）许可：受理公安机关审查后，对符合配购条件的核发民用枪支配购证件。打印本页关闭窗口浏览次数：135次主题词：枪支支配许可证-点击收起详细信息索引号01123743-3-0101-2015-000005文号发布机构荆门市公安局发布日期2015-07-16公开范围面向社会公开方式主动公开CopyRight2015　湖北省公安厅版权所有　鄂ICP备07008323号",
                "kinfoName": "民用枪支配购许可证件核发",
                "kinfoGuid": "5971b859-8367-4d96-a501-da513caebd58",
                "categoryName": "社会治安管理",
                "visitTimes": 5
            },
            {
                "publishTime": "2022-07-31 18:09:01",
                "kinfoContent": "只要是年满16周岁且未满60周岁、女未满55周岁的城乡居民（在校学生除外）；未与用人单位建立劳动关系；未参加企业职工基本养老保险，均可持本人有效身份证件就近到辖区政务服务中心社保经办机构办理灵活就业人员参保。参保后可按我市今年公布的社保缴费标准缴费。",
                "kinfoName": "应届毕业生缴纳社保的相关政策。",
                "kinfoGuid": "59970c97-c81a-4929-8cfb-5c786547a775",
                "categoryName": "职工养老保险",
                "visitTimes": 7
            },
            {
                "publishTime": "2022-07-31 18:09:01",
                "kinfoContent": "采用以考代评的方式，参加全国经济师中级职称考试。具体报名条件见湖北人事考试网。http://www.hbsrsksy.cn/hbksy/001/001001/001001002/20220402/2afade05-a6ca-4ad7-b34e-035292135cdf.html",
                "kinfoName": "经济师中级职称评定政策。",
                "kinfoGuid": "5b9faee2-848d-4354-95ff-d202450ac21f",
                "categoryName": "职称评定",
                "visitTimes": 5
            },
            {
                "publishTime": "2022-07-31 18:09:01",
                "kinfoContent": "农村养老保险缴费方式（手机下载鄂汇办或楚税通app、东街地税大厅或邮政和农业银行都可缴费）",
                "kinfoName": "农村养老保险缴费方式。",
                "kinfoGuid": "5c1d2eae-4898-47be-acb3-c5f2b46f8b4e",
                "categoryName": "居民养老保险",
                "visitTimes": 36
            },
            {
                "publishTime": "2022-07-31 18:09:01",
                "kinfoContent": "食品保质期，指食品在标明的贮存条件下保持品质的期限。",
                "kinfoName": "什么是食品保质期？",
                "kinfoGuid": "5e2c3f9a-93de-4001-a8f0-79f8c8f2a166",
                "categoryName": "商品质量管理",
                "visitTimes": 7
            },
            {
                "publishTime": "2022-07-31 18:09:01",
                "kinfoContent": "当前位置：　荆门市公安局　　行政许可事项　　正文Ⅰ、Ⅱ级焰火晚会许可　　1、事项名称：Ⅰ、Ⅱ级焰火晚会许可　　2、设定依据：《烟花爆竹安全管理条例》　　3、申请条件：举办焰火晚会以及其他大型焰火燃放活动，应当按照举办的时间、地点、环境、活动性质、规模以及燃放烟花爆竹的种类、规格和数量，确定危险等级，按照分级管理的规定，向有关人民政府公安部门提出申请。　　4、办理材料：　　（一）举办焰火晚会以及其他大型焰火燃放活动的时间、地点、环境、活动性质、规模；　　（二）燃放烟花爆竹的种类、规格、数量；　　（三）燃放作业方案；　　（四）燃放作业单位、作业人员符合行业标准规定条件的证明。　　5、办理地点：市公安局治安支队治安科　　6、办理时间：20个工作日，不收取费用　　7、联系电话：8882121　　8、办理流程：　　（一）受理工作：申请举办焰火晚会以及其他大型焰火燃放活动，主办单位应当按照分级管理的规定，向有关人民政府公安部门提出申请。如申请人所提交的资料齐全，且符合法定要求，应立即受理；如所交资料存在可以当场更正的错误，应告知申请人当场更正，更正后，应立即受理；如所交资料不齐全或不符合法定要求，应立即告知申请人，须补齐的全部内容。　　（二）审核工作：受理申请的公安部门应当自受理之日起20日内对提交的有关材料进行审查。　　（三）许可工作：对符合条件的，核发《焰火燃放许可证》；对不符合条件的应当说明理由。打印本页关闭窗口浏览次数：78次主题词：晚会-点击收起详细信息索引号01123743-3-0101-2015-000007文号发布机构荆门市公安局发布日期2015-07-15公开范围面向社会公开方式主动公开CopyRight2015　湖北省公安厅版权所有　鄂ICP备07008323号",
                "kinfoName": "Ⅰ、Ⅱ级焰火晚会许可",
                "kinfoGuid": "5f505e8a-4d58-489d-865c-aefda478b799",
                "categoryName": "社会治安管理",
                "visitTimes": 6
            },
            {
                "publishTime": "2022-07-31 18:09:01",
                "kinfoContent": "食品添加剂，指为改善食品品质和色、香、味以及为防腐、保鲜和加工工艺的需要而加入食品中的人工合成或者天然物质，包括营养强化剂。",
                "kinfoName": "什么是食品添加剂？",
                "kinfoGuid": "5feb57be-e3b1-4126-b3cd-ea59e28840b0",
                "categoryName": "商品质量管理",
                "visitTimes": 7
            },
            {
                "publishTime": "2022-07-31 18:09:01",
                "kinfoContent": "实体社保卡可在定点医疗机构、定点药店购药结算，社保卡不能购药等问题，一是因整合城乡居民基本医疗参保账户多个造成不能正常使用，二是社保卡密码等问题。参保账户多个可联系医保局解决，密码问题可在人社社保卡窗口办理。",
                "kinfoName": "社保卡为何在药店无法购药。",
                "kinfoGuid": "65c0b7cd-1cad-480e-875f-37c3cac92630",
                "categoryName": "职工医疗保险",
                "visitTimes": 17
            },
            {
                "publishTime": "2022-07-31 18:09:01",
                "kinfoContent": "1.企业、事业单位、相关组织及个人委托检验：企业、事业单位、相关组织及个人委托检验→各直属单位对口受理→服务大厅办理承检手续→提供委托单位（个人）申请；填写委托检验单；提供样品→样品资料审验合格收样→按约定时限领取检验报告2.政府有关部门和特别重大的委托检验业务：政府有关部门和特别重大的委托检验业务→中心技术业务部受理→签订委托检验协议（合同）→指定服务窗口办理委托检验手续；填写委托检验单；提供样品→样品资料审验合格收样→按约定时限领取检验报告和质量分析3.上级部门下达的任务：上级部门下达抽验任务→各所制定实施方案→组织人员开展抽样封样→各所样品验收；样品登记→按规定时限出具检验报告和报送相关资料",
                "kinfoName": "委托检验办事流程",
                "kinfoGuid": "66e0718b-0ac7-4c70-85f6-2bccf9d73294",
                "categoryName": "商品质量管理",
                "visitTimes": 8
            },
            {
                "publishTime": "2022-07-31 18:09:01",
                "kinfoContent": "欢迎您访问荆门市政务服务网！荆门市湖北省人民政府门户网站全文检索新闻检索事项检索搜索登录注册首页自然人办事法人办事政务公开政民互动办事指南对政务服务事项的办事主体、依据、流程、材料、注意事项等内容所作的指导性说明事项名称：机动车驾驶证核发分享：收费打印收藏全文下载在线申请在线预约展现方式：文本展现图文展现表格展现扫描二维码手机查看基础信息设定依据办理流程问题咨询事项评价服务对象个人办结时限办结时限1工作日，法定时限5工作日受理机构荆门市公安局电话：0724-2635599受理条件1、年龄条件;2、身体条件;申请材料办理时间周一至周五：上午8:00-12:00下午:14:30-17:30办理地点荆门市东宝区海慧路附1号驾考中心办证大厅申请形式窗口申请在线申请结果样本准予许可查看更多+鄂ICP备05011090号-1主办：湖北省人民政府行政审批制度改革办公室承办单位：湖北省信息中心技术支持：湖北省信息中心咨询服务邮箱：zwfw@hbbsdt.gov.cn;hubeizwfw@163.com建议使用1366*768分辨率/IE9.0或以上浏览器访问达到最佳效果",
                "kinfoName": "机动车驾驶证核发",
                "kinfoGuid": "6a357da4-ce1b-42de-9c10-a66cd7a9b76c",
                "categoryName": "驾驶员管理",
                "visitTimes": 15
            },
            {
                "publishTime": "2022-07-31 18:09:01",
                "kinfoContent": "生产者、销售者对抽查检验的结果有异议的，可以自收到检验结果之日起十五日内向实施监督抽查的市场监督管理部门或者其上级市场监督管理部门申请复检，由受理复检的市场监督管理部门作出复检结论。",
                "kinfoName": "《中华人民共和国产品质量法》规定生产者、销售者对抽查检验的结果有异议怎么办？",
                "kinfoGuid": "6b4c4c8e-79e8-465c-a3e0-939a6559785b",
                "categoryName": "商品质量管理",
                "visitTimes": 6
            },
            {
                "publishTime": "2022-07-31 18:09:01",
                "kinfoContent": "单位社会保险缴费申报单位社会保险缴费申报服务说明：为参保单位办理月度缴费申报：参保单位进行缴费申报，根据单位已申报的缴费基数和缴费人数，生成单位应缴数据和个人应缴数据。",
                "kinfoName": "省社保系统单位社会保险缴费申报如何操作",
                "kinfoGuid": "6bdb3e9b-12be-4b06-b6ff-ec2eadf0948c",
                "categoryName": "职工医疗保险",
                "visitTimes": 7
            },
            {
                "publishTime": "2022-07-31 18:09:01",
                "kinfoContent": "一、适用范围：本服务指南适用于办理化肥、建材、石油、食品包装等工业产品质量检验检测业务二、基础要素（一）事项名称：化肥、建材、石油、食品包装等工业产品质量检验检测（二）申请形式：窗口申请（三）受理机构：荆门市工业产品质量检验所技术业务室地址：荆门市掇刀区兴隆大道227号荆门市公共检验检测中心南楼一楼大厅工业产品业务办理窗口；业务受理电话：0724-6903299（四）实施机构：荆门市工业产品质量检验所（五）法律依据：《中华人民共和国产品质量法》、《湖北省实施中华人民共和国产品质量法办法》、《中华人民共和国标准化法》、《中华人民共和国标准化法实施条例》、《中华人民共和国计量法》、《产品质量监督抽查管理暂行办法》（六）职能:承担化肥、建材、石油、食品包装等产品质量检验检测工作。（七）受理要求:1.受理条件（1）营业执照或自然人身份证复印件；（2）外观、数量符合技术要求的样品；（3）委托人身份证复印件。（八）办结时限：受理检验1个工作日内回复；检验服务时限：化肥产品检验办结时限为11~19个工作日；建材产品检验办结时限为16~34个工作日；石油产品检验办结时限为10工作日、食品包装（可降解生物及塑料制品）24工作日~100日。（一次性委托检验数量超过10批次或遇如新冠病毒等非不可抗拒力因素，双方按协议期限办理）（九）申请材料：化肥、建材、石油、食品包装等产品质量检验检测申请：1.营业执照、单位法人证书或委托人确认（十）结果名称：1.检验报告（十一）收费：本事项不收费（十二）办理时间：法定工作日上午8:30-12:00下午14:30-18:00（夏季上午8:30-12:00下午15:00-18:00以市政府通知为准）（十三）办事流程：（1）申请申请人通过办理窗口进行申请。（2）受理工作人员对申请人提交的申请资料及检验样品外观、数量等进行审核，资料齐全并在检测资质范围内，予以受理；材料不齐全或不符合要求的，告知申请人补正；不在检测资质范围内的，不予受理。（3）检验根据检验协议书和国家相关标准、规范要求进行检验。（4）报告出具检验报告经编制、审核、签发后出具，报告完成。（5）申请人按检验协议书确定的时间和方式领取检验报告。",
                "kinfoName": "市工业产品质量检验所工业产品检验服务指南",
                "kinfoGuid": "6e931c7e-e1e9-46cc-9e4f-909ede431829",
                "categoryName": "商品质量管理",
                "visitTimes": 5
            },
            {
                "publishTime": "2022-07-31 18:09:01",
                "kinfoContent": "请在有食品生产经营许可证的单位购买食品，如果发现食品存在安全问题，请向食品行政管理部门举报，由投诉受理部门抽样检验。",
                "kinfoName": "买的食品不放心，是否可以检验?",
                "kinfoGuid": "6f46fca8-dc26-43bf-83ae-c837f105e13a",
                "categoryName": "商品质量管理",
                "visitTimes": 7
            },
            {
                "publishTime": "2022-07-31 18:09:01",
                "kinfoContent": "一、适用范围：本服务指南适用于办理农产品质量检验业务二、基础要素（一）事项名称：农产品、原粮及油料、食用植物油、畜禽产品等质量检验（二）申请形式：窗口申请（三）受理机构：荆门市农产品质量检验所业务技术室地址：荆门市掇刀区兴隆大道227号承办人员：雷彬办公室电话：0724-6661022手机：13872938818（四）实施机构：荆门市农产品质量检验所（五）法律依据：1.《中华人民共和国农产品质量安全法》2.《中华人民共和国食品安全法》3.《粮食质量监管实施办法》(试行)（六）职能：从事农产品、原粮及油料、食用植物油、畜禽产品等质量检验检测工作。（七）受理要求1.受理条件（1）营业执照（2）委托检验单（3）标准资料（八）办结时限：是否受理检验1个工作日内回复，农产品、原粮及油料中单个样品定量检验7个工作日；原粮及油料、食用植物油单个样品理化指标检验3个工作日；畜禽产品单个样品定量检验7个工作日。多批次样品检验与客户协商完成时限。（九）申请材料：农产品检验申请材料1.营业执照，复印件1份；2.检验委托单，窗口领取，填写完整，纸质版原件1份；3.质量标准，纸质版原件1份；4.其他要求：真实，合法，完整。（十）结果名称：1.检验报告书（十一）收费:本事项不收费（十二）办理时间:法定工作日上午8:30-12:00下午14:30-18:00（夏季上午8:30-12:00下午15:00-18:00以市政府通知为准）（十三）办事流程办事流程:1.申请申请人通过办理窗口进行申请。2.受理对申请人提交的申请资料进行审核，资料齐全并在检测资质范围内，予以受理；材料不齐全或不符合要求的，告知申请人补正；不在检测资质范围内的，不予受理。3.检验根据检验协议书和国家相关标准、规范要求进行检验。4.报告出具检验报告经编制、审核、签发后出具，报告完成。5.报告领取申请人按检验协议书确定的时间和方式领取检验报告。",
                "kinfoName": "市农产品质量检验所农产品质量检验服务指南",
                "kinfoGuid": "7c129ad1-754e-4c80-9606-a59594930cfb",
                "categoryName": "商品质量管理",
                "visitTimes": 5
            },
            {
                "publishTime": "2022-07-31 18:09:01",
                "kinfoContent": "办理个人参保登记时只审核年龄不审核户籍所在地。只要是年满16周岁且未满60周岁、女未满55周岁的城乡居民（在校学生除外）；未与用人单位建立劳动关系；未参加企业职工基本养老保险，均可持本人有效身份证件就近到辖区政务服务中心社保经办机构办理灵活就业人员参保。参保后可按今年公布的社保缴费标准缴费。",
                "kinfoName": "外地务工人员以灵活就业人员身份如何缴纳养老保险。",
                "kinfoGuid": "80646bf7-a348-43be-bb97-f213bbf5c322",
                "categoryName": "职工养老保险",
                "visitTimes": 24
            },
            {
                "publishTime": "2022-07-31 18:09:01",
                "kinfoContent": "《中华人民共和国食品安全法》规定：对依照本法规定实施的检验结论有异议的，食品生产经营者可以自收到检验结论之日起七个工作日内向实施抽样检验的食品安全监督管理部门或者其上一级食品安全监督管理部门提出复检申请，由受理复检申请的食品安全监督管理部门在公布的复检机构名录中随机确定复检机构进行复检。复检机构出具的复检结论为最终检验结论。复检机构与初检机构不得为同一机构。复检机构名录由国务院认证认可监督管理、食品安全监督管理、卫生行政、农业行政等部门共同公布。采用国家规定的快速检测方法对食用农产品进行抽查检测，被抽查人对检测结果有异议的，可以自收到检测结果时起四小时内申请复检。复检不得采用快速检测方法。",
                "kinfoName": "食品生产经营者对依照《中华人民共和国食品安全法》规定实施的检验结论有异议的怎么办？",
                "kinfoGuid": "8456d55c-1a80-452a-940a-4dadfe372acf",
                "categoryName": "商品质量管理",
                "visitTimes": 6
            },
            {
                "publishTime": "2022-07-31 18:09:01",
                "kinfoContent": "对于个别农户生产的农产品，因为生产量小，不具有代表性，原则上不受理委托检验。",
                "kinfoName": "个别农户生产的农产品委托检验是否受理？",
                "kinfoGuid": "855ed1fd-78b0-4688-8721-c3df5f458e94",
                "categoryName": "商品质量管理",
                "visitTimes": 5
            },
            {
                "publishTime": "2022-07-31 18:09:01",
                "kinfoContent": "FWZN-42080000000001123743300000048000-2017禁毒宣传服务指南荆门市公安局2017年12月14日发布2017年12月14日实施禁毒宣传服务指南一、适用范围本服务指南适用于办理禁毒宣传业务二、基础要素（一）事项名称禁毒宣传（二）事项代码42080000000001123743300000048000（三）办件类型承诺件即办件（四）申请形式窗口申请网上申请（五）服务对象（六）受理机构无（七）实施机构荆门市公安局（八）设定依据1.《中华人民共和国禁毒法》（2007年12月29日第十届全国人民代表大会常务委员会第三十一次会议通过）第十一条、第十二条、第十六条、第十七条2.《中共中央国务院关于加强禁毒工作的意见》（中发〔2014〕6号）3.《关于印发＜全国青少年毒品预防教育规划＞（2016-2018）的通知》（禁毒办发〔2015〕1号）（九）受理要求1.受理条件无（十）法定办结时限无（十一）承诺办结时限无（十二）申请材料禁毒宣传申请材料序号材料名称材料来源材料要求材料性质材料份数1毒品知识宣传，防范毒品危害宣传，参与禁毒斗争宣传电子版和纸质版原件1份复印件1份其他要求：（十三）结果名称1.禁毒宣传（十四）结果样本结果样本见附件（十五）收费本事项不收费（十六）办理时间周一至周五：上午8:00-12:00下午:14:30-17:30（十七）办理地点荆门市漳河新区深圳大道88号.荆门市公安局禁毒支队（十八）办理流程图三、办理流程（一）禁毒宣传，禁毒知识咨询毒品知识宣传，防范毒品危害宣传四、申请人权利和义务（一）监督投诉荆门市公安局督察支队，电话0724-8882065附件：1.（结果样本）",
                "kinfoName": "禁毒宣传",
                "kinfoGuid": "86247528-bfbc-4013-a86a-2b6943b2d845",
                "categoryName": "社会治安管理",
                "visitTimes": 6
            }
        ]
    }
}