{
    "status": {
        "code": "1",
        "text": "获取知识列表成功！"
    },
    "custom": {
        "num": 6088,
        "infoList": [
            {
                "publishTime": "2023-03-09 10:09:44",
                "kinfoContent": "何为两部制电价？两部制电价就是将电价分为基本电价和电度电价两个部分，一是以客户的实际用电量来计算电费的电度电价；二是以客户接入系统的用电容量或最大需量计算的基本电价。",
                "kinfoName": "何为两部制电价？",
                "ispublic": "true",
                "kinfoGuid": "87d91f3d-ea7d-4ea3-bc5b-9b9ff6156c4d",
                "categoryName": "供电服务",
                "visitTimes": 536
            },
            {
                "publishTime": "2023-03-08 17:04:24",
                "kinfoContent": "超编制、超标准配备公务用车的；违反规定将公务用车登记在下属单位、企业或者个人名下的；公车私用、私车公养，或者既领取公务交通补贴又违规使用公务用车的；换用、借用、占用下属单位或者其他单位和个人的车辆，或者擅自接受企事业单位和个人赠送车辆的；挪用或者固定给个人使用执法执勤、机要通信、特种专业技术等公务用车的；为公务用车增加高档配置或者豪华内饰的；在车辆维修等费用中虚列名目或者夹带其他费用，为非本单位车辆报销运行维护费用的；违规处置公务用车的；违规租用社会车辆的；有其他违反公务用车配备使用管理规定行为的。",
                "kinfoName": "党政机关有哪些情形要依纪依法追究相关人员责任",
                "ispublic": "true",
                "kinfoGuid": "f6071c13-5684-44ab-9050-d3deb07eaf8a",
                "categoryName": "机构职能",
                "visitTimes": 15
            },
            {
                "publishTime": "2023-03-08 17:00:55",
                "kinfoContent": "公务交通补贴保障区域内公务用车使用情形为：执行重大抢险救灾、事故处理、突发事件处置等不可预测的特殊任务；参加陪同中央、省、外地来荆调研、检查、考察及接待工作，参加商务及外事活动。",
                "kinfoName": "公务交通补贴保障区域内公务用车使用情形包括哪些？",
                "ispublic": "true",
                "kinfoGuid": "ba19c3ab-baa9-4386-9785-00ef46827ea4",
                "categoryName": "机构职能",
                "visitTimes": 31
            },
            {
                "publishTime": "2023-03-08 16:51:34",
                "kinfoContent": "市级公务交通补贴保障区域确定为东宝区龙泉街道和泉口街道、荆门高新区·掇刀区白庙街道、掇刀石街道和兴隆街道、漳河新区双喜街道六个街道的中心城区范围。即：南到原武荆高速路入口；北到东宝工业园；东至襄荆高速入口；西至仙女公墓；漳河方向西外环以内；麻城方向市标以内。各县（市、区）根据各地实际情况，合理确定本地区公务交通补贴保障区域范围。",
                "kinfoName": "公务交通补贴保障区域范围如何界定？",
                "ispublic": "true",
                "kinfoGuid": "6359c016-7957-4c13-a962-ec6e7302231d",
                "categoryName": "机构职能",
                "visitTimes": 47
            },
            {
                "publishTime": "2023-03-07 16:15:35",
                "kinfoContent": "公交车，指在城市道路上遵循固定路线，有或者无固定班次时刻，承载旅客出行的机动车辆。一般外形为方型，有窗，设置座位。公共汽车时速一般在25-50公里，不会超过60公里，又称为公共汽车、公汽或巴士，其中“公交”是公共交通的简称，公交车台湾地区又称为公车、客运或巴士，在香港和澳门，则多称为巴士。公交车对社会影响巨大，对城市发展起着最基本的推动作用。公交车使市民体验到彼此间前所未有的接近，也缩短城市和邻近村镇间的距离、往来频繁。",
                "kinfoName": "公交车的定义",
                "ispublic": "true",
                "kinfoGuid": "a3a7e978-8718-45c7-83d3-dde23195f27e",
                "categoryName": "公交服务",
                "visitTimes": 16
            },
            {
                "publishTime": "2023-03-07 16:12:35",
                "kinfoContent": "公交车作为日常最常见的交通工具，很少有人重视他的安全，但是一旦公交车出现事故，那么造成的危害也很大。乘坐公交车时必知的安全常识1、严禁携带易燃、易爆、有毒等危险品乘坐公交车。2、车厢内禁止吸烟、吐痰、乱扔果皮纸屑，不准向车外吐痰、乱扔杂物，以保持环境卫生。3、乘坐公交车，不得将身体的任何部位伸出车外，禁止有碍行车安全的行为。4、乘客所购车票，限当日当次乘坐有效，车辆因故不能运行时，由司乘人员安排换乘其它车辆。5、乘坐公交车，应当主动购票、出示月票或其它有效证件，并接受司乘或稽查人员的查验。6、身高达到120厘米的儿童乘坐公交车，应当购票;儿童集体乘车的，按实际人数购票。7、由于乘客原因，造成车辆设施或其它财产损失及人身伤害的，由当事人负责赔偿。8、严禁无票乘车，严禁使用废票或过期证乘车，严禁使用伪造的票证或利用他人票证私换照片乘车。9、乘客违反本规则，当车司乘人员或稽查人员有权处理;情节严重的交公安机关处理。10、运营车辆发生事故或治安事件，乘客有协助司乘人员处置的义务。11、上车请不要争先恐后，乱拥乱挤，乘坐公交车须在站亭或指定的地点依次候车，等车靠边停稳后，依秩序上下，不要在车内吃用竹签或其它金属物串联的食物，乘车要尊老爱幼讲礼貌，见老弱病残及孕妇要主动让座。乘车前的防护事项有哪些1、不要在马路上挥手叫停公交车。2、选择好自己要乘坐的公交车线路，到公交站台处排队依次上车。3、候车时一定要站在站台上，不要妨碍公交车辆正常靠站停车，从而危害自己的人身安全。4、上车前确认公交车是哪一条线路的，因为公交车停靠站时，往往是几条线路的公交车在同一个站台，人多时容易乘错车。5、现在城市公交都是无人售票，乘车前需要提前准备好零钞、乘车卡或乘车二维码。6、要文明乘车，相互谦让，不要争先恐后地拥挤在车门口，防止扒窃分子乘机作案。乘车中的注意事项有哪些1、上车后不要挤在车门边，往里边走，见空处站稳，并拉好扶手，头、手、身体不要伸出窗外，否则容易发生伤害事故。2、不要在车内吃用竹签或其他金属物串联的食物，如肉串等，以防刹车或拥挤时造成伤害。3、文明乘车，尊老爱幼讲礼貌，见到老弱病残及孕妇请主动让座。4、不要在车内嬉戏打闹，以免影响自身安全及其他乘客的安全。5、乘坐公交车时，要爱惜车内的设施，不要乱涂乱画，更不要用小刀在车上乱刻乱画。6、乘坐公交车时，严禁携带易燃、易爆物品上车。7、女生遇到有人故意往你身上挤时，你可以大叫：干嘛一直挤呀!或者瞪着他看，然后站离对方。8、车辆快到站时，要提前做好下车的准备。9、车辆发生事故时，不要惊慌，听从驾驶员的指挥，有序地离开车厢。",
                "kinfoName": "乘坐公交车时必知的安全常识",
                "ispublic": "true",
                "kinfoGuid": "f550c2f1-84ae-45e8-a55f-8caf2a20217e",
                "categoryName": "公交服务",
                "visitTimes": 2
            },
            {
                "publishTime": "2023-03-06 17:23:38",
                "kinfoContent": "化肥中钾（K2O）能够促进光合作用，缺钾使光合作用减弱。钾能明显地提高植物对氮的吸收和利用，并很快转化为蛋白质。钾还能促进植物经济用水。由于钾离子能较多地累积在作物细胞之中，因此使细胞渗透压增加并使水分从低浓度的土壤溶液中向高浓度的根细胞中移动。在钾供应充足时，作物能有效地利用水分，并保持在体内，减少水分的蒸腾作用。反之钾素供应不足时，碳水化合物代谢受到干扰，光合作用受抑制，而呼吸作用加强。因此，缺钾时植株抗逆能力减弱，易受病害侵袭，果实品质下降。钾的另一特点是有助于作物的抗逆性。钾的重要生理作用之一是增强细胞对环境条件的调节作用。钾能增强植物对各种不良状况的忍受能力，如干旱、低温、含盐量、病虫危害、倒伏等。总之，在施肥之前最好请专业人员或专业公司进行现场测土配方来达到适量用肥。",
                "kinfoName": "化肥中钾（K2O）对作物的作用和影响",
                "ispublic": "true",
                "kinfoGuid": "8f6a2a94-5ad2-4640-8991-c9691deb632f",
                "categoryName": "农资农技",
                "visitTimes": 13
            },
            {
                "publishTime": "2023-03-06 16:54:00",
                "kinfoContent": "“智改数转”：指智能化改造和数字化转型，是通过智能化和数字化为企业双向赋能，促进信息技术和制造业深度融合。",
                "kinfoName": "什么是“智改数转”？",
                "ispublic": "true",
                "kinfoGuid": "014e5ee3-06a2-499a-a22b-71e812fef01e",
                "categoryName": "机构职能",
                "visitTimes": 0
            },
            {
                "publishTime": "2023-03-06 16:53:10",
                "kinfoContent": "“多测合一”：指按照“一次委托、联合测绘、成果共享”的原则，在建设项目审批全流程，将测绘内容相近或属于同一审批阶段的多个测绘业务，整合为一个测绘业务，由项目业主委托一家具备相应资质的测绘服务机构开展测绘活动，成果供相关主管部门审批使用。　　",
                "kinfoName": "什么是“多测合一”？",
                "ispublic": "true",
                "kinfoGuid": "a41160fb-f6b2-4394-90fd-972df18cc92a",
                "categoryName": "机构职能",
                "visitTimes": 0
            },
            {
                "publishTime": "2023-03-06 16:51:36",
                "kinfoContent": "属于。2021年11月9日施行的《社会消防技术服务管理规定》规定，消防技术服务机构是指从事消防设施维护保养检测、消防安全评估等社会消防技术服务活动的企业。",
                "kinfoName": "从事消防设施维保的单位是否属于消防技术服务机构",
                "ispublic": "true",
                "kinfoGuid": "d1b70531-3bbc-4666-9b16-c9ef1781705e",
                "categoryName": "消防安全",
                "visitTimes": 17
            },
            {
                "publishTime": "2023-03-06 16:51:06",
                "kinfoContent": "“四上”企业：规上工业企业、资质等级建筑业企业、限额以上批零住餐企业、国家重点服务业企业。",
                "kinfoName": "什么是“四上”企业？",
                "ispublic": "true",
                "kinfoGuid": "b2ad19d2-939a-4a15-a578-4d254f0015a7",
                "categoryName": "机构职能",
                "visitTimes": 19
            },
            {
                "publishTime": "2023-03-06 16:50:55",
                "kinfoContent": "属于。2021年11月9日施行的《社会消防技术服务管理规定》规定，消防技术服务机构是指从事消防设施维护保养检测、消防安全评估等社会消防技术服务活动的企业。",
                "kinfoName": "从事消防设施检测的单位是否属于消防技术服务机构",
                "ispublic": "true",
                "kinfoGuid": "6219ffb8-5b0e-429c-a5f6-7755d6089aba",
                "categoryName": "消防安全",
                "visitTimes": 11
            },
            {
                "publishTime": "2023-03-06 16:50:03",
                "kinfoContent": "（1）企业法人资格；（2）工作场所建筑面积不少于100平方米；（3）消防技术服务基础设备和消防安全评估设备配备符合附表1和附表3的要求；（4）注册消防工程师不少于2人，且企业技术负责人由一级注册消防工程师担任；（5）健全的消防安全评估过程控制体系。",
                "kinfoName": "从事消防安全评估服务的消防技术服务机构应具备什么条件",
                "ispublic": "true",
                "kinfoGuid": "180d0ac6-f651-4639-822c-a37051f9686c",
                "categoryName": "消防安全",
                "visitTimes": 13
            },
            {
                "publishTime": "2023-03-06 15:46:08",
                "kinfoContent": "按《荆门市城市管理条例》第三十四条第二款“排放油烟的饮食服务业经营者应当安装油烟净化设施并保持正常使用，或者采取其他油烟净化措施，使油烟达标排放。”　第七十三条“违反本条例第三十四条规定的，由城市管理部门按照以下规定予以处罚：（一）饮食服务业经营者未安装和未正常使用油烟净化设施，超标准排放油烟的，责令改正，并处五千元以上二万元以下罚款；拒不改正的，责令停业整治。”",
                "kinfoName": "排放油烟的饮食服务业处罚标准是什么？",
                "ispublic": "true",
                "kinfoGuid": "76257139-de84-4cd6-9a14-7a2bde0a983e",
                "categoryName": "环境执法",
                "visitTimes": 47
            },
            {
                "publishTime": "2023-03-06 15:45:26",
                "kinfoContent": "按《中华人民共和国大气污染防治法》第四十五条产生含挥发性有机物废气的生产和服务活动，应当在密闭空间或者设备中进行，并按照规定安装、使用污染防治设施；无法密闭的，应当采取措施减少废气排放。第一百零八条第一段第一项“违反本法规定，有下列行为之一的，由县级以上人民政府生态环境主管部门责令改正，处二万元以上二十万元以下的罚款；拒不改正的，责令停产整治：（一）产生含挥发性有机物废气的生产和服务活动，未在密闭空间或者设备中进行，未按照规定安装、使用污染防治设施，或者未采取减少废气排放措施的；”",
                "kinfoName": "无组织排放挥发性有机物废气的生产和服务活动处罚标准是什么？",
                "ispublic": "true",
                "kinfoGuid": "c78a6c17-789e-4d09-a453-f5ad0bb934b6",
                "categoryName": "固体污染",
                "visitTimes": 20
            },
            {
                "publishTime": "2023-03-06 08:45:16",
                "kinfoContent": "预购商品房预告登记转房屋所有权登记与预购商品房抵押预告登记转抵押权登记（合并登记）一、申请材料不动产抵押登记申请书暨主债权合同及抵押合同集成表。二、办理流程申请受理登记发证（一窗办结）。三、收费标准及依据住宅80元/件，非住宅550元/件。四、办理时限：4小时。温馨提示：1.原不动产登记证明（收回注销）2、我中心提供免费邮寄不动产权证书服务，您可在申请办证时选择邮寄。3、办公地址：荆门市双喜大道5号龙泉大厦西附楼一楼4、服务咨询电话：0724-2222138",
                "kinfoName": "预购商品房预告登记转房屋所有权登记与预购商品房抵押预告登记转抵押权登记（合并登记）",
                "ispublic": "true",
                "kinfoGuid": "fd767053-c906-4793-b435-5c9fa92d0500",
                "categoryName": "不动产权服务",
                "visitTimes": 43
            },
            {
                "publishTime": "2023-03-06 08:43:49",
                "kinfoContent": "预购商品房预告登记与预购商品房抵押预告登记（合并登记）一、申请材料不动产抵押登记申请书暨主债权合同及抵押合同集成表。二、办理流程申请受理发证（一窗办结）。三、收费标准：不收费。四、办理时限：4小时。温馨提示：1、我中心提供免费邮寄不动产权证书服务，您可在申请办证时选择邮寄。2、办公地址：荆门市双喜大道5号龙泉大厦西附楼一楼3、服务咨询电话：0724-2222138",
                "kinfoName": "预购商品房预告登记与预购商品房抵押预告登记 （合并登记）",
                "ispublic": "true",
                "kinfoGuid": "c2252362-3d27-4133-af02-dec27f5c40e8",
                "categoryName": "不动产权服务",
                "visitTimes": 13
            },
            {
                "publishTime": "2023-03-06 08:42:45",
                "kinfoContent": "预告登记的注销一、申请材料债权消灭或者权利人放弃预告登记的材料。二、办理流程申请受理办结。三、收费标准：不收费。四、办理时限：即时办结。温馨提示：1、原不动产登记证明（收回注销）2、办公地址：荆门市双喜大道5号龙泉大厦西附楼一楼3、服务咨询电话：0724-2222138",
                "kinfoName": "预告登记的注销",
                "ispublic": "true",
                "kinfoGuid": "bbbaa8e6-38b1-4ff5-9c78-dd45794c1120",
                "categoryName": "不动产权服务",
                "visitTimes": 20
            },
            {
                "publishTime": "2023-03-03 15:43:01",
                "kinfoContent": "参保人员因死亡注销职工医保个人账户时，个人账户余额以现金形式一次性支付给其法定继承人；参保人员因跨统筹地区转移职工医保参保关系时，个人账户余额转移至新参保地职工医保个人账户。",
                "kinfoName": "医保卡需注销，账户余额如何使用？",
                "ispublic": "true",
                "kinfoGuid": "f5bc87b6-9d9b-4c88-9b6e-877fde2b820b",
                "categoryName": "职工医疗保险",
                "visitTimes": 53
            },
            {
                "publishTime": "2023-03-03 15:41:37",
                "kinfoContent": "可以办理职工医保退费的情形共三种：一是达到退休不再缴费条件的退休人员，在申请办理退休清算手续时，多缴的部分医保费，退返给单位或个人；二是灵活就业人员再就业时，存在单位缴费和灵活就业状态重复缴纳的部分医保费，退返给个人；三是参保人员死亡，死亡次月起多缴的部分医保费，退返给单位或参保人的法定继承人。城乡居民医保在集中缴费期内重复缴纳的医保费，退返给个人。",
                "kinfoName": "什么情况下医保可以退费？",
                "ispublic": "true",
                "kinfoGuid": "232261ed-efe3-4430-970d-e5f263fd82cf",
                "categoryName": "职工医疗保险",
                "visitTimes": 44
            }
        ]
    }
}