{
    "status": {
        "code": "1",
        "text": "获取知识列表成功！"
    },
    "custom": {
        "num": 6088,
        "infoList": [
            {
                "publishTime": "2022-08-30 22:48:13",
                "kinfoContent": "阳光助残创业扶持“双百工程”每年在农村扶持400名残疾人创办农家店，成为农家小店主，在集镇扶持400名残疾人开展创业项目，成为集镇小老板，并给予符合条件的农家小店主和集镇小老板每人每年5000元的资金扶持。项目申报条件:农家小店主(含残疾人规模种植养殖户)和集镇小老板对象必须是湖北省籍在本省境内处于就业年龄段的残疾人，且同时具备以下条件:1.农家小店主(1)店主本人持有二代残疾人证，具备经营管理能力;(2)农家店处于集镇范围外的农村地区，贫困地区优先;(3)农家店营业面积要求达到10平方以上，网店除外;(4)稳定经营6个月以上，需提供相关佐证材料。2.集镇小老板(1)创业者本人持有二代残疾人证，具备创业能力;(2)创业项目优先扶持当年新创办项目，并取得了工商营业执照;(3)稳定经营6个月以上(以工商营业执照为准)。政策依据:《湖北省残疾人就业促进“十三五”实施方案》(鄂残联发(2017)30号)《湖北省阳光助残创业扶持“双百工程”实施方案(修订)》(鄂残联办发(2018)6号)关于印发《湖北省阳光助残创业扶持“双百工程”项目资金管理办法》的通知(鄂残联办函(2018)16号)",
                "kinfoName": "残疾人农家小店主、集镇小老板资金扶持政策",
                "kinfoGuid": "56c77068-7ba9-4dff-a8e0-cd57857bb47e",
                "categoryName": "创业优惠政策",
                "visitTimes": 7
            },
            {
                "publishTime": "2022-08-30 22:48:13",
                "kinfoContent": "儿童时期超重和肥胖除了对健康有直接影响外，还明显增加成年期肥胖的危险，应加以预防和控制。但儿童减重与成年人不同，儿童需要充足能量和营养素摄入以保证正常的生长发育不受损害。对儿童体重控制的重点是防止体重增长太快。",
                "kinfoName": "儿童应如何减重？",
                "kinfoGuid": "56ec8096-369c-49af-a225-45bffb6edd98",
                "categoryName": "卫生医疗知识",
                "visitTimes": 7
            },
            {
                "publishTime": "2022-08-30 22:48:13",
                "kinfoContent": "汽油对中枢神经系统有麻醉作用，高浓度的汽油可以使呼吸麻痹；汽油也刺激皮肤、黏膜。",
                "kinfoName": "汽油有些什么危害和毒性?",
                "kinfoGuid": "5f9469b7-1744-4cc3-84f1-6b6c3bb1723f",
                "categoryName": "卫生医疗知识",
                "visitTimes": 7
            },
            {
                "publishTime": "2022-08-30 22:48:13",
                "kinfoContent": "用多种杀菌药物的泡板组装的联合化疗（MDT）（1板/月），在家规则治疗。在治疗中患者仍可从事其日常生活、工作、就学，不应令其退学或采取停职留薪等措施。在规则服MDT后每半年一次临床监测，每年一次细菌监测，并应告知患者，在有可疑情况（神经痛、新皮损、皮肤麻木等症状）时，及时就诊。",
                "kinfoName": "麻风病治疗原则",
                "kinfoGuid": "6060830f-11a2-4787-9a60-f8c35e764aae",
                "categoryName": "卫生医疗知识",
                "visitTimes": 7
            },
            {
                "publishTime": "2022-08-30 22:48:13",
                "kinfoContent": "含铁质丰富的有动物肝脏、动物全血；其次是瘦肉、蛋黄、鸡、鱼、虾和豆类。绿叶蔬菜中含铁多的有苜蓿、菠菜、芹菜、油菜、苋菜、荠菜、黄花菜、番茄等。水果中以杏、桃、李、葡萄干、红枣、樱桃等含铁较多，干果有核桃，其它如海带、红糖、芝麻酱也含有铁。动物性食物中的铁吸收利用率相对较高，而蔬菜水果中的铁为非血红素铁，吸收利用率较低。另外，维生素C有促进铁吸收的作用。",
                "kinfoName": "那些食物对补铁有好处？",
                "kinfoGuid": "60a34dc6-e183-4c7a-8aed-e524944d33bb",
                "categoryName": "卫生医疗知识",
                "visitTimes": 7
            },
            {
                "publishTime": "2022-08-30 22:48:13",
                "kinfoContent": "患有痢疾、伤寒、病毒性肝炎、活动期肺结核、化脓性或渗出性皮肤病以及其他有碍公共卫生的疾病，治愈前不得在公共场所从事直接为顾客服务的工作。",
                "kinfoName": "公共场所从业人员患有哪些疾病不得从事直接为顾客服务的工作？",
                "kinfoGuid": "618f9ad4-7b23-4d38-98b4-38373cdf1dd7",
                "categoryName": "卫生医疗知识",
                "visitTimes": 7
            },
            {
                "publishTime": "2022-08-30 22:48:13",
                "kinfoContent": "麻疹是由麻疹病毒引起的一种以发热、呼吸道卡他（咳嗽、流涕等）和遍及全身斑丘疹为特征的急性呼吸道传染病。",
                "kinfoName": "什么是麻疹？",
                "kinfoGuid": "6282cbac-30c0-4f3d-a658-694b352d6cd6",
                "categoryName": "卫生医疗知识",
                "visitTimes": 7
            },
            {
                "publishTime": "2022-08-30 22:48:13",
                "kinfoContent": "1.统筹研究和组织实施“三农”工作的发展战略、中长期规划、重大政策。贯彻落实市委、市政府关于中国农谷建设战略部署。组织起草农业农村有关地方性法规、市政府规章草案。指导农业综合执法。参与涉农财税、价格、收储、金融保险等政策措施制定。2.统筹推动发展农村社会事业、农村公共服务、农村文化、农村基础设施和乡村治理。组织开展高标准农田建设、美丽宜居乡村建设。牵头组织改善农村人居环境。指导农村精神文明和优秀农耕文化建设。指导农业行业安全生产工作。3.组织落实深化农村经济体制改革和巩固完善农村基本经营制度的政策。承担农民承包地、农村宅基地改革和管理有关工作。承担农村集体产权制度改革，指导农村集体经济组织发展和集体资产管理工作。指导农民合作经济组织、农业社会化服务体系、新型农业经营主体建设与发展。负责全市农村经营管理和农民负担监督管理工作。4.指导乡村特色产业、农产品加工业、休闲农业和乡镇企业发展工作。协调有关部门制定全市农产品加工业中长期发展规划，指导推进农产品精深加工产业发展。提出促进大宗农产品流通的建议，培育、保护农业品牌。发布农业农村经济信息，监测分析农业农村经济运行。承担农业统计和农业农村信息化有关工作。5.负责种植业、畜牧业、渔业、农垦、农业机械化等农业各产业的监督管理。指导粮食、油料、畜禽、水产等农产品生产。指导蔬菜、水果、茶叶、蚕桑、中药材等经济作物生产可持续发展。组织构建现代农业产业体系、生产体系、经营体系，指导农业标准化生产。负责渔政渔港监督管理。6.负责农产品质量安全监督管理。组织开展农产品质量安全监测、追溯、风险评估。参与制定农产品质量安全地方标准并会同有关部门组织实施。7.指导农用地、渔业水域以及农业生物物种资源的保护与管理，负责水生野生动植物保护、耕地及永久基本农田质量保护工作。指导农产品产地环境管理和农业清洁生产。指导设施农业、生态循环农业、节水农业发展以及农村可再生能源综合开发利用、农业生物质产业发展。牵头管理外来物种。配合做好农业资源区划相关工作。8.负责有关农业生产资料和农业投入品的监督管理、配合做好农业生产资料市场体系建设。组织实施兽药质量、兽药残留限量和残留检测方法国家标准。组织兽医医政、兽药药政药检工作，负责执业兽医和畜禽屠宰行业管理。9.负责农业防灾减灾、农作物重大病虫害防治工作。指导动植物防疫检疫体系建设，组织、监督全市动植物防疫检疫工作，发布疫情并组织扑灭。10.负责农业投资管理。提出农业投融资体制机制改革建议。编制市级投资安排的农业投资项目建设规划，提出农业投资规模和方向、扶持农业农村发展财政项目的建议，按市政府规定权限，审批市级财政专项安排的农业投资项目，负责农业投资项目资金安排和监督管理。11.推动农业科技体制改革和农业科技创新体系建设。制定农业科研、农技推广的规划、计划和有关政策，会同有关部门组织全市农业科技创新体系和农业产业技术体系建设，实施科教兴农战略，组织重大科研专项和技术推广项目的遴选及实施。组织实施农业领域的高新技术和应用技术研究、农业科技成果转化和技术推广。负责农业科技成果管理，组织引进国内外农业先进技术，指导农技推广体系改革与建设。负责农业转基因生物安全监督管理和农业植物新品种保护。12.指导农业农村人才工作。拟订农业农村人才队伍建设规划并组织实施，指导农业教育和农业职业技能开发，参与实施新型职业农民培育、农业科技人才培养和农村实用人才培训工程。13.牵头开展农业对外合作工作。承办政府间农业涉外事务，组织开展农业贸易促进和有关对外交流合作，组织实施有关农业援外项目。",
                "kinfoName": "荆门市农业农村局主要职责",
                "kinfoGuid": "6352d76d-17bf-40c1-9a75-c46f4489bf0f",
                "categoryName": "机构职能",
                "visitTimes": 13
            },
            {
                "publishTime": "2022-08-30 22:48:13",
                "kinfoContent": "(1)空气中的尘土、沙粒；(2)昆虫及农业生产中的谷壳；(3)磨床或车床上溅出的金属或木屑；(4)采矿区的细小矿石等。儿童在尘土、沙粒飞扬的环境中行走，在打谷场、厂矿作业区附近玩耍，易发生眼内异物伤害。",
                "kinfoName": "眼内异物伤害发生原因有哪些？",
                "kinfoGuid": "6364814e-4d80-48f8-a0bd-f96449c07afd",
                "categoryName": "卫生医疗知识",
                "visitTimes": 7
            },
            {
                "publishTime": "2022-08-30 22:48:13",
                "kinfoContent": "艾滋病病毒抗体检测的流程包括初筛试验和确证试验。由于初筛试验成本低，且简便快速，所以用于筛查。但是初筛试验结果呈阳性反应时，有可能是假阳性，还需要再做确证试验，确证试验结果阳性者才能报告为艾滋病病毒抗体阳性。",
                "kinfoName": "为什么艾滋病病毒抗体检测需要作初筛试验和确证试验？",
                "kinfoGuid": "64773941-4067-4350-b72e-a7d5d47d5e2f",
                "categoryName": "卫生医疗知识",
                "visitTimes": 7
            },
            {
                "publishTime": "2022-08-30 22:48:13",
                "kinfoContent": "根据突发公共卫生事件性质、危害程度、涉及范围，突发公共卫生事件划分为特别重大（Ⅰ级）、重大（Ⅱ级）、较大（Ⅲ级）和一般（Ⅳ级）四级。",
                "kinfoName": "突发公共卫生事件是如何分级的？",
                "kinfoGuid": "66565c9a-7d85-4564-ba95-e990ef15cbd4",
                "categoryName": "公共卫生安全",
                "visitTimes": 7
            },
            {
                "publishTime": "2022-08-30 22:48:13",
                "kinfoContent": "在所在地通过当地卫生计生行政部门认可的具有接种资质的乡镇卫生院、社区卫生服务中心或村卫生室均可接种。",
                "kinfoName": "在哪里能接种到百白破疫苗疫苗",
                "kinfoGuid": "668cc30b-c6d3-4090-ba7b-32d86b3c1350",
                "categoryName": "卫生医疗知识",
                "visitTimes": 7
            },
            {
                "publishTime": "2022-08-30 22:48:13",
                "kinfoContent": "心脏有节奏的收缩、舒张推动血液在血管内流动，流动的血液对动脉血管壁的侧压力称之为血压。心脏收缩时血液对动脉血管壁产生的最高压力为收缩压，俗称“高压”；心脏舒张时血液对动脉血管壁产生的压力为舒张压，俗称“低压”。通常血压的单位用mmHg表示，如116/72mmHg，其中“116”代表收缩压，“72”代表舒张压。",
                "kinfoName": "什么叫血压，血压如何计数？",
                "kinfoGuid": "68d37430-d230-4d8e-9e7f-e16d049420cc",
                "categoryName": "卫生医疗知识",
                "visitTimes": 7
            },
            {
                "publishTime": "2022-08-30 22:48:13",
                "kinfoContent": "砷化氢多为某些工业生产过程中产生的废气，或当含砷金属(如铅、铜、金、银、镉、锌、钒等)和酸作用，或用水浇熄灼热的含砷炉渣时，可产生砷化氢气体。工业用硫酸和盐酸中常含少量砷，与金属作用也可产生砷化氢。乙炔的生产和使用，用酸清洗金属，生产合成染料，氰化法提取金银，蓄电池充电，含砷矿渣的冶炼和保存，特别是接触潮湿空气或雨水均可产生砷化氢气体。由无机砷或有机砷水解可产生砷化氢。如鱼舱中海鱼腐败使有机砷转化为砷化氢致使下舱工人中毒。",
                "kinfoName": "哪些工作场所可能接触砷化氢?",
                "kinfoGuid": "68d6df1f-965b-4adb-933c-0cf73f15b3a5",
                "categoryName": "卫生医疗知识",
                "visitTimes": 7
            },
            {
                "publishTime": "2022-08-30 22:48:13",
                "kinfoContent": "湖北健康码进行了功能升级这几类人员通过鄂汇办APP、支付宝打开湖北健康码将收到弹窗提醒谁会收到弹窗提示？来鄂返鄂人员弹窗：前一日来（返）鄂且在鄂停留4小时以上，尚未在社区报备的人员，其打开湖北健康码将收到弹窗提示。（若已在社区报备，且社区已完成信息上报，将不会收到弹窗提示）购买四类药品弹窗：为进一步完善疫情防控零售药店预警机制，实现对高风险人员的源头管控，购买“四类药品”（退热、抗生素、抗病毒、咳嗽感冒药品）的人员，打开健康码将收到弹窗提示。",
                "kinfoName": "湖北健康码功能更新：这几类人员将收到弹窗",
                "kinfoGuid": "69631597-9173-40b4-9443-43901d56383b",
                "categoryName": "卫生医疗知识",
                "visitTimes": 7
            },
            {
                "publishTime": "2022-08-30 22:48:13",
                "kinfoContent": "儿童在6月龄时按照我国现行免疫规划程序，需要接种乙肝疫苗第3剂和A群脑膜炎球菌疫苗第1剂。",
                "kinfoName": "儿童在6月龄时需要接种何种疫苗？",
                "kinfoGuid": "719efa1c-0b5b-4edd-948a-c046a3df70d4",
                "categoryName": "卫生医疗知识",
                "visitTimes": 7
            },
            {
                "publishTime": "2022-08-30 22:48:13",
                "kinfoContent": "扶持残疾人自主就业创业对残疾人自主就业创业的，按照有关规定免收管理类、登记类和证照类等有关行政事业性收费和具有强制垄断性的经营性收费;征得行业协会商会同意，适当减免或降低会费及其它服务收费。生产经营困难的，可依法申请降低住房公积金缴存比例或缓缴，待效益好转后再提高缴存比例或补缴。残疾人创办具有公益性、福利性且在民政部门登记为民办非企业单位的经营场所用电、用水、用气、用热按照民用标准收取。政策依据:《关于扶持残疾人自主就业创业的意见》(残联发(2018)6号)",
                "kinfoName": "残疾人自主就业创业免收或降低缴费的相关费用",
                "kinfoGuid": "72d277e6-f931-44d0-83b0-4dcdeacee797",
                "categoryName": "创业优惠政策",
                "visitTimes": 9
            },
            {
                "publishTime": "2022-08-30 22:48:13",
                "kinfoContent": "菌盖不规则球形，红褐色，后变成咖啡褐色，扭曲呈人大脑沟回的形状。宽高各为2~10厘米，菌肉薄，蜡质，很脆。菌柄短，灰白色。主要生长在春秋季。此菌中毒多因将它误认为羊肚菌而引起。引起红细胞溶解。中毒表现：进食6~12小时后出现腹痛、腹泻等症状，很快出现溶血表现，",
                "kinfoName": "鹿花菌",
                "kinfoGuid": "73a4c823-0760-448c-ae2b-d1c08257d525",
                "categoryName": "卫生医疗知识",
                "visitTimes": 8
            },
            {
                "publishTime": "2022-08-30 22:48:13",
                "kinfoContent": "乙肝发病比较隐匿，临床上常表现为低热、乏力、食欲减退、恶心、呕吐、厌油、腹胀、肝区疼痛，可出现巩膜黄、尿黄如茶水样等黄疸症状、轻度发热等。急性感染乙肝病毒者，如果未能清除病毒，乙肝病毒表面抗原阳性持续6个月以上，则转为慢性。对于慢性乙肝病毒感染者，目前尚无有效药物可以彻底清除乙肝病毒。重症者可能发展为肝硬化和原发性干细胞癌，甚至导致死亡。",
                "kinfoName": "乙肝的主要症状有哪些？",
                "kinfoGuid": "74cb61f5-7303-4161-85fa-c083273af26c",
                "categoryName": "卫生医疗知识",
                "visitTimes": 8
            },
            {
                "publishTime": "2022-08-30 22:48:13",
                "kinfoContent": "办错了业务怎么进行撤销？答：新系统办理的业务可以自行申请撤销（未审核且未发生后续关联业务），已审核业务不支持撤销，已发生后续关联业务的，按照业务办理先后顺序倒序撤销。月度核定只能在【单位社会保险缴费撤销申报】功能撤销，核定单只能在【单位社会保险费应缴认定单及退费单据撤销】功能撤销。",
                "kinfoName": "湖北省社保网申系统办错了业务怎么进行撤销？",
                "kinfoGuid": "7552efbd-7435-4eb8-9f65-b5906f6a1c51",
                "categoryName": "职工养老保险",
                "visitTimes": 8
            }
        ]
    }
}